MANIFEST.in
README.txt
setup.py
trac_WorkflowActionButtons.egg-info/PKG-INFO
trac_WorkflowActionButtons.egg-info/SOURCES.txt
trac_WorkflowActionButtons.egg-info/dependency_links.txt
trac_WorkflowActionButtons.egg-info/entry_points.txt
trac_WorkflowActionButtons.egg-info/not-zip-safe
trac_WorkflowActionButtons.egg-info/top_level.txt
workflow_actionbuttons/__init__.py
workflow_actionbuttons/api.py
workflow_actionbuttons/web_ui.py
workflow_actionbuttons/htdocs/.gitignore
workflow_actionbuttons/htdocs/fontawesome/css/font-awesome.css
workflow_actionbuttons/htdocs/fontawesome/css/font-awesome.min.css
workflow_actionbuttons/htdocs/fontawesome/fonts/FontAwesome.otf
workflow_actionbuttons/htdocs/fontawesome/fonts/fontawesome-webfont.eot
workflow_actionbuttons/htdocs/fontawesome/fonts/fontawesome-webfont.svg
workflow_actionbuttons/htdocs/fontawesome/fonts/fontawesome-webfont.ttf
workflow_actionbuttons/htdocs/fontawesome/fonts/fontawesome-webfont.woff
workflow_actionbuttons/htdocs/jquery.modal/close.png
workflow_actionbuttons/htdocs/jquery.modal/jquery.modal.css
workflow_actionbuttons/htdocs/jquery.modal/jquery.modal.min.js
workflow_actionbuttons/htdocs/main/actionbuttons.css
workflow_actionbuttons/htdocs/main/actionbuttons.js