Metadata-Version: 1.0
Name: trac-WorkflowActionButtons
Version: 0.2
Summary: Adds one-click buttons to Trac tickets for workflow operations (closing, reassigning, commenting)
Home-page: http://trac-hacks.org/wiki/WorkflowActionButtonsPlugin
Author: Ethan Jucovy
Author-email: ejucovy@gmail.com
License: BSD
Keywords: trac plugin
Platform: UNKNOWN
